jvt/__init__.py
jvt/convpass.py
jvt/deit.py
jvt/levit.py
jvt/mae.py
jvt/vit.py
jvt-0.1.0.dist-info/METADATA
jvt-0.1.0.dist-info/WHEEL
jvt-0.1.0.dist-info/top_level.txt
jvt-0.1.0.dist-info/RECORD
